{
    "name": "particles",
    "id": "particles",
    "capacity": 15,
    "disposeOnStop": false,
    "manualEmitCount": -1,
    "emitterId": "emitter0",
    "particleEmitterType": {
        "type": "SphereParticleEmitter",
        "radius": 2.5,
        "radiusRange": 1,
        "directionRandomizer": 1
    },
    "texture": {
        "tags": null,
        "url": "https://assets.babylonjs.com/particles/textures/sun/T_SunFlare.png",
        "uOffset": 0,
        "vOffset": 0,
        "uScale": 1,
        "vScale": 1,
        "uAng": 0,
        "vAng": 0,
        "wAng": 0,
        "uRotationCenter": 0.5,
        "vRotationCenter": 0.5,
        "wRotationCenter": 0.5,
        "homogeneousRotationInUVTransform": false,
        "isBlocking": true,
        "name": "https://assets.babylonjs.com/particles/textures/sun/T_SunFlare.png",
        "hasAlpha": false,
        "getAlphaFromRGB": false,
        "level": 1,
        "coordinatesIndex": 0,
        "coordinatesMode": 0,
        "wrapU": 1,
        "wrapV": 1,
        "wrapR": 1,
        "anisotropicFilteringLevel": 4,
        "isCube": false,
        "is3D": false,
        "is2DArray": false,
        "gammaSpace": true,
        "invertZ": false,
        "lodLevelInAlpha": false,
        "lodGenerationOffset": 0,
        "lodGenerationScale": 0,
        "linearSpecularLOD": false,
        "isRenderTarget": false,
        "animations": [],
        "invertY": true,
        "samplingMode": 3,
        "_useSRGBBuffer": false
    },
    "isLocal": false,
    "animations": [],
    "beginAnimationOnStart": false,
    "beginAnimationFrom": 0,
    "beginAnimationTo": 60,
    "beginAnimationLoop": false,
    "startDelay": 0,
    "renderingGroupId": 0,
    "isBillboardBased": true,
    "billboardMode": 7,
    "minAngularSpeed": 0,
    "maxAngularSpeed": 0,
    "minSize": 1,
    "maxSize": 1,
    "minScaleX": 0.5,
    "maxScaleX": 5,
    "minScaleY": 0.5,
    "maxScaleY": 5,
    "minEmitPower": 0.05,
    "maxEmitPower": 0.25,
    "minLifeTime": 10,
    "maxLifeTime": 10,
    "emitRate": 10,
    "gravity": [
        0,
        0,
        0
    ],
    "noiseStrength": [
        10,
        10,
        10
    ],
    "color1": [
        1,
        1,
        0,
        1
    ],
    "color2": [
        1,
        0.5,
        0,
        1
    ],
    "colorDead": [
        0,
        0,
        0,
        1
    ],
    "updateSpeed": 0.01,
    "targetStopDuration": 0,
    "blendMode": 2,
    "preWarmCycles": 100,
    "preWarmStepOffset": 10,
    "minInitialRotation": -6.283185307179586,
    "maxInitialRotation": 6.283185307179586,
    "startSpriteCellID": 0,
    "endSpriteCellID": 0,
    "spriteCellChangeSpeed": 1,
    "spriteCellWidth": 0,
    "spriteCellHeight": 0,
    "spriteRandomStartCell": false,
    "isAnimationSheetEnabled": false,
    "activeParticleCount": 15,
    "randomTextureSize": 16384,
    "customShader": null
}